nifty7/__init__.py
nifty7/domain_tuple.py
nifty7/extra.py
nifty7/fft.py
nifty7/field.py
nifty7/linearization.py
nifty7/logger.py
nifty7/multi_domain.py
nifty7/multi_field.py
nifty7/operator_spectrum.py
nifty7/operator_tree_optimiser.py
nifty7/plot.py
nifty7/pointwise.py
nifty7/probing.py
nifty7/random.py
nifty7/sugar.py
nifty7/utilities.py
nifty7/version.py
nifty7/domains/__init__.py
nifty7/domains/dof_space.py
nifty7/domains/domain.py
nifty7/domains/gl_space.py
nifty7/domains/hp_space.py
nifty7/domains/lm_space.py
nifty7/domains/power_space.py
nifty7/domains/rg_space.py
nifty7/domains/structured_domain.py
nifty7/domains/unstructured_domain.py
nifty7/library/__init__.py
nifty7/library/adjust_variances.py
nifty7/library/correlated_fields.py
nifty7/library/correlated_fields_simple.py
nifty7/library/dynamic_operator.py
nifty7/library/light_cone_operator.py
nifty7/library/los_response.py
nifty7/library/nft.py
nifty7/library/special_distributions.py
nifty7/library/variational_models.py
nifty7/library/wiener_filter_curvature.py
nifty7/minimization/__init__.py
nifty7/minimization/conjugate_gradient.py
nifty7/minimization/descent_minimizers.py
nifty7/minimization/energy.py
nifty7/minimization/energy_adapter.py
nifty7/minimization/iteration_controllers.py
nifty7/minimization/kl_energies.py
nifty7/minimization/line_search.py
nifty7/minimization/minimizer.py
nifty7/minimization/nonlinear_cg.py
nifty7/minimization/quadratic_energy.py
nifty7/minimization/scipy_minimizer.py
nifty7/minimization/stochastic_minimizer.py
nifty7/operators/__init__.py
nifty7/operators/adder.py
nifty7/operators/block_diagonal_operator.py
nifty7/operators/chain_operator.py
nifty7/operators/contraction_operator.py
nifty7/operators/convolution_operators.py
nifty7/operators/diagonal_operator.py
nifty7/operators/distributors.py
nifty7/operators/domain_tuple_field_inserter.py
nifty7/operators/einsum.py
nifty7/operators/endomorphic_operator.py
nifty7/operators/energy_operators.py
nifty7-7.5.dist-info/COPYING
nifty7-7.5.dist-info/METADATA
nifty7-7.5.dist-info/WHEEL
nifty7-7.5.dist-info/top_level.txt
nifty7-7.5.dist-info/RECORD
