Metadata-Version: 2.1
Name: nifty7
Version: 7.5
Summary: Library for signal inference algorithms that operate regardless of the underlying grids and their resolutions.
Home-page: https://ift.pages.mpcdf.de/nifty/
Author: Martin Reinecke
Author-email: martin@mpa-garching.mpg.de
License: GPLv3
Project-URL: Bug Tracker, https://gitlab.mpcdf.mpg.de/ift/nifty/issues
Project-URL: Documentation, https://ift.pages.mpcdf.de/nifty/
Project-URL: Source Code, https://gitlab.mpcdf.mpg.de/ift/nifty
Project-URL: Changelog, https://gitlab.mpcdf.mpg.de/ift/nifty/-/blob/NIFTy_7/ChangeLog
Platform: UNKNOWN
Classifier: Development Status :: 5 - Production/Stable
Classifier: Topic :: Scientific/Engineering :: Mathematics
Classifier: Topic :: Scientific/Engineering :: Physics
Classifier: License :: OSI Approved :: GNU General Public License v3 (GPLv3)
Classifier: Operating System :: OS Independent
Classifier: Programming Language :: Python
Classifier: Intended Audience :: Science/Research
Requires-Python: >=3.6
License-File: COPYING
Requires-Dist: scipy (>=1.4.1)
Requires-Dist: numpy (>=1.17)
